qbt_migrate/__init__.py
qbt_migrate/classes.py
qbt_migrate/cli.py
qbt_migrate/enums.py
qbt_migrate/methods.py
qbt_migrate-2.3.2.dist-info/entry_points.txt
qbt_migrate-2.3.2.dist-info/LICENSE.md
qbt_migrate-2.3.2.dist-info/WHEEL
qbt_migrate-2.3.2.dist-info/METADATA
qbt_migrate-2.3.2.dist-info/RECORD
