Metadata-Version: 2.1
Name: qbt_migrate
Version: 2.3.2
Summary: qBt Migrate, change the paths of existing torrents in qBittorrent, as well as convert paths to Windows/Linux/Mac
Author-email: Justin Slay <justin.slay@gmail.com>
Requires-Python: >=3.8
Classifier: Development Status :: 5 - Production/Stable
Classifier: Intended Audience :: Developers
Classifier: Intended Audience :: End Users/Desktop
Classifier: Intended Audience :: Information Technology
Classifier: License :: OSI Approved :: MIT License
Classifier: Programming Language :: Python :: 3.8
Classifier: Programming Language :: Python :: 3.9
Classifier: Programming Language :: Python :: 3.10
Classifier: Programming Language :: Python :: 3.11
Classifier: Topic :: Communications :: File Sharing
Classifier: Topic :: Software Development :: Libraries
Classifier: Topic :: Software Development :: Libraries :: Python Modules
Classifier: Topic :: System :: Recovery Tools
Classifier: Typing :: Typed
Requires-Dist: bencode.py==4.0.0
Requires-Dist: black ; extra == "dev"
Requires-Dist: coverage ; extra == "dev"
Requires-Dist: diff-cover ; extra == "dev"
Requires-Dist: flake8 ; extra == "dev"
Requires-Dist: isort ; extra == "dev"
Requires-Dist: pre-commit ; extra == "dev"
Requires-Dist: pytest>=2.7.3 ; extra == "dev"
Requires-Dist: tox ; extra == "test"
Project-URL: Source, https://github.com/jslay88/qbt_migrate
Provides-Extra: dev
Provides-Extra: test
